[{"heading": "103.9", "latitude": 6.1612593, "longitude": -75.6378744, "speed": "7.88"},
{"heading": "103.9", "latitude": 6.1612042, "longitude": -75.6376675, "speed": "7.89"},
{"heading": "104.1", "latitude": 6.1611809, "longitude": -75.637574, "speed": "7.90"},
{"heading": "104.1", "latitude": 6.1611454, "longitude": -75.637432, "speed": "7.90"},
{"heading": "104.0", "latitude": 6.1611265, "longitude": -75.63736, "speed": "7.90"},
{"heading": "104.0", "latitude": 6.1611099, "longitude": -75.6372915, "speed": "7.90"},
{"heading": "114.1", "latitude": 6.1610987, "longitude": -75.6372288, "speed": "7.57"},
{"heading": "69.9", "latitude": 6.1611057, "longitude": -75.6371524, "speed": "7.27"},
{"heading": "41.0", "latitude": 6.161139, "longitude": -75.6371157, "speed": "7.60"},
{"heading": "38.3", "latitude": 6.1611929, "longitude": -75.6370759, "speed": "7.64"},
{"heading": "38.0", "latitude": 6.1612468, "longitude": -75.6370332, "speed": "7.64"},
{"heading": "38.0", "latitude": 6.1613016, "longitude": -75.6369901, "speed": "7.65"},
{"heading": "38.0", "latitude": 6.1613552, "longitude": -75.6369482, "speed": "7.64"},
{"heading": "38.0", "latitude": 6.1614085, "longitude": -75.636905, "speed": "7.64"},
{"heading": "38.0", "latitude": 6.1614632, "longitude": -75.6368618, "speed": "7.65"},
{"heading": "103.3", "latitude": 6.1614846, "longitude": -75.6368453, "speed": "6.67"},
{"heading": "112.7", "latitude": 6.1614541, "longitude": -75.6367894, "speed": "7.13"},
{"heading": "113.9", "latitude": 6.1614256, "longitude": -75.6367299, "speed": "7.19"},
{"heading": "114.0", "latitude": 6.1613984, "longitude": -75.6366715, "speed": "7.20"},
{"heading": "114.0", "latitude": 6.1613717, "longitude": -75.6366117, "speed": "7.20"},
{"heading": "114.0", "latitude": 6.161345, "longitude": -75.6365531, "speed": "7.20"},
{"heading": "114.0", "latitude": 6.1613183, "longitude": -75.6364933, "speed": "7.20"},
{"heading": "159.1", "latitude": 6.1612799, "longitude": -75.6364137, "speed": "12.75"},
{"heading": "165.3", "latitude": 6.1611704, "longitude": -75.6363795, "speed": "12.79"},
{"heading": "126.7", "latitude": 6.16106, "longitude": -75.6362937, "speed": "16.28"},
{"heading": "110.2", "latitude": 6.1610068, "longitude": -75.6362219, "speed": "16.67"},
{"heading": "107.7", "latitude": 6.1609686, "longitude": -75.6360546, "speed": "16.26"},
{"heading": "107.3", "latitude": 6.1609249, "longitude": -75.6359106, "speed": "16.19"},
{"heading": "107.1", "latitude": 6.1608817, "longitude": -75.6357701, "speed": "16.17"},
{"heading": "107.2", "latitude": 6.1608369, "longitude": -75.6356314, "speed": "16.18"},
{"heading": "107.1", "latitude": 6.1607934, "longitude": -75.6354917, "speed": "16.17"},
{"heading": "107.1", "latitude": 6.16075, "longitude": -75.6353516, "speed": "16.17"},
{"heading": "107.2", "latitude": 6.1607052, "longitude": -75.635213, "speed": "16.18"},
{"heading": "104.9", "latitude": 6.1606782, "longitude": -75.6351216, "speed": "16.10"},
{"heading": "106.1", "latitude": 6.16064, "longitude": -75.6349801, "speed": "16.10"},
{"heading": "106.8", "latitude": 6.160597, "longitude": -75.63484, "speed": "16.15"},
{"heading": "107.0", "latitude": 6.1605535, "longitude": -75.6347, "speed": "16.16"},
{"heading": "107.0", "latitude": 6.1605101, "longitude": -75.6345599, "speed": "16.17"},
{"heading": "107.4", "latitude": 6.1604431, "longitude": -75.6343432, "speed": "16.41"},
{"heading": "106.1", "latitude": 6.1604, "longitude": -75.6341902, "speed": "16.26"},
{"heading": "105.3", "latitude": 6.1603615, "longitude": -75.6340469, "speed": "16.19"},
{"heading": "107.7", "latitude": 6.1603201, "longitude": -75.6339093, "speed": "16.07"},
{"heading": "107.6", "latitude": 6.1602618, "longitude": -75.6337443, "speed": "16.31"},
{"heading": "105.4", "latitude": 6.1602377, "longitude": -75.6336602, "speed": "16.07"},
{"heading": "107.5", "latitude": 6.1602085, "longitude": -75.6335626, "speed": "15.91"},
{"heading": "109.3", "latitude": 6.1601589, "longitude": -75.6334307, "speed": "16.08"},
{"heading": "112.1", "latitude": 6.160101, "longitude": -75.6332734, "speed": "16.14"},
{"heading": "112.9", "latitude": 6.1600421, "longitude": -75.6331353, "speed": "16.16"},
{"heading": "114.8", "latitude": 6.1599308, "longitude": -75.6328789, "speed": "16.60"},
{"heading": "112.1", "latitude": 6.1598658, "longitude": -75.632724, "speed": "15.94"},
{"heading": "115.0", "latitude": 6.159801, "longitude": -75.6325729, "speed": "16.14"},
{"heading": "115.8", "latitude": 6.1597354, "longitude": -75.6324386, "speed": "16.17"},
{"heading": "116.1", "latitude": 6.1596437, "longitude": -75.6322491, "speed": "16.58"},
{"heading": "113.3", "latitude": 6.1595978, "longitude": -75.632145, "speed": "16.12"},
{"heading": "113.1", "latitude": 6.15954, "longitude": -75.63201, "speed": "16.17"},
{"heading": "113.1", "latitude": 6.1594818, "longitude": -75.6318751, "speed": "16.18"},
{"heading": "113.1", "latitude": 6.1594234, "longitude": -75.6317414, "speed": "16.17"},
{"heading": "112.4", "latitude": 6.1593785, "longitude": -75.6316353, "speed": "16.02"},
{"heading": "112.8", "latitude": 6.1593218, "longitude": -75.6315044, "speed": "16.12"},
{"heading": "113.0", "latitude": 6.1592635, "longitude": -75.6313714, "speed": "16.16"},
{"heading": "114.0", "latitude": 6.1592007, "longitude": -75.6312395, "speed": "16.17"},
{"heading": "114.5", "latitude": 6.1591313, "longitude": -75.6310835, "speed": "16.29"},
{"heading": "114.0", "latitude": 6.1590327, "longitude": -75.6308585, "speed": "16.34"},
{"heading": "113.2", "latitude": 6.1589713, "longitude": -75.6307144, "speed": "16.18"},
{"heading": "112.9", "latitude": 6.1589146, "longitude": -75.630579, "speed": "16.13"},
{"heading": "112.8", "latitude": 6.158858, "longitude": -75.6304442, "speed": "16.13"},
{"heading": "109.1", "latitude": 6.1588356, "longitude": -75.6303851, "speed": "15.74"},
{"heading": "111.0", "latitude": 6.1587454, "longitude": -75.6301555, "speed": "16.56"},
{"heading": "105.6", "latitude": 6.1586997, "longitude": -75.6300022, "speed": "16.40"},
{"heading": "108.3", "latitude": 6.1586597, "longitude": -75.6298684, "speed": "16.07"},
{"heading": "109.6", "latitude": 6.1586088, "longitude": -75.6297314, "speed": "16.13"},
{"heading": "109.5", "latitude": 6.1585865, "longitude": -75.6296676, "speed": "15.79"},
{"heading": "112.3", "latitude": 6.158513, "longitude": -75.6294959, "speed": "16.27"},
{"heading": "112.4", "latitude": 6.1584537, "longitude": -75.6293541, "speed": "16.23"},
{"heading": "109.7", "latitude": 6.1584001, "longitude": -75.6292111, "speed": "16.30"},
{"heading": "108.2", "latitude": 6.1583414, "longitude": -75.6290361, "speed": "16.37"},
{"heading": "106.8", "latitude": 6.1582981, "longitude": -75.6288891, "speed": "16.24"},
{"heading": "108.5", "latitude": 6.1582101, "longitude": -75.6286209, "speed": "16.13"},
{"heading": "106.0", "latitude": 6.1581962, "longitude": -75.6285486, "speed": "15.89"},
{"heading": "108.2", "latitude": 6.1581682, "longitude": -75.6284613, "speed": "15.83"},
{"heading": "117.3", "latitude": 6.1581017, "longitude": -75.6282951, "speed": "16.00"},
{"heading": "120.6", "latitude": 6.1579501, "longitude": -75.6280387, "speed": "16.51"},
{"heading": "121.5", "latitude": 6.1579049, "longitude": -75.6279594, "speed": "15.37"},
{"heading": "123.3", "latitude": 6.1578271, "longitude": -75.6278487, "speed": "15.89"},
{"heading": "123.9", "latitude": 6.1577438, "longitude": -75.6277297, "speed": "16.10"},
{"heading": "124.1", "latitude": 6.1576603, "longitude": -75.6276098, "speed": "16.15"},
{"heading": "124.1", "latitude": 6.1575769, "longitude": -75.6274883, "speed": "16.18"},
{"heading": "125.5", "latitude": 6.157464, "longitude": -75.627326, "speed": "16.63"},
{"heading": "127.1", "latitude": 6.1573796, "longitude": -75.6272006, "speed": "16.27"},
{"heading": "126.1", "latitude": 6.1572726, "longitude": -75.6270541, "speed": "16.55"},
{"heading": "126.8", "latitude": 6.1572158, "longitude": -75.6269741, "speed": "15.75"},
{"heading": "124.5", "latitude": 6.1571478, "longitude": -75.6268859, "speed": "15.80"},
{"heading": "126.7", "latitude": 6.1570429, "longitude": -75.6267436, "speed": "16.35"},
{"heading": "126.6", "latitude": 6.1569418, "longitude": -75.6266103, "speed": "16.42"},
{"heading": "126.3", "latitude": 6.1568534, "longitude": -75.6264916, "speed": "16.25"},
{"heading": "126.7", "latitude": 6.1567342, "longitude": -75.6263267, "speed": "16.73"},
{"heading": "128.2", "latitude": 6.1566492, "longitude": -75.6262095, "speed": "16.24"},
{"heading": "128.9", "latitude": 6.1565554, "longitude": -75.6260964, "speed": "16.19"},
{"heading": "129.1", "latitude": 6.1564619, "longitude": -75.6259846, "speed": "16.17"},
{"heading": "137.4", "latitude": 6.1563869, "longitude": -75.6258968, "speed": "15.94"},
{"heading": "162.5", "latitude": 6.156251, "longitude": -75.6258014, "speed": "21.79"},
{"heading": "147.9", "latitude": 6.1560859, "longitude": -75.6257469, "speed": "21.03"},
{"heading": "157.7", "latitude": 6.1559812, "longitude": -75.6256669, "speed": "21.41"},
{"heading": "177.2", "latitude": 6.1558174, "longitude": -75.6256559, "speed": "20.24"},
{"heading": "186.1", "latitude": 6.1556222, "longitude": -75.6256956, "speed": "20.66"},
{"heading": "188.4", "latitude": 6.1554311, "longitude": -75.6257288, "speed": "20.78"},
{"heading": "189.2", "latitude": 6.1552493, "longitude": -75.6257582, "speed": "20.76"},
{"heading": "190.5", "latitude": 6.1550777, "longitude": -75.6257901, "speed": "20.71"},
{"heading": "185.9", "latitude": 6.1547343, "longitude": -75.6258305, "speed": "20.89"},
{"heading": "182.8", "latitude": 6.1545414, "longitude": -75.6258315, "speed": "20.81"},
{"heading": "178.7", "latitude": 6.1542165, "longitude": -75.6258304, "speed": "20.76"},
{"heading": "171.8", "latitude": 6.1540253, "longitude": -75.6257936, "speed": "20.74"},
{"heading": "169.1", "latitude": 6.1538273, "longitude": -75.6257483, "speed": "20.63"},
{"heading": "159.6", "latitude": 6.1536921, "longitude": -75.6257177, "speed": "19.84"},
{"heading": "152.9", "latitude": 6.1535352, "longitude": -75.6256272, "speed": "20.33"},
{"heading": "151.1", "latitude": 6.1533877, "longitude": -75.6255401, "speed": "20.44"},
{"heading": "147.6", "latitude": 6.1530823, "longitude": -75.6253603, "speed": "22.61"},
{"heading": "159.8", "latitude": 6.1528809, "longitude": -75.625287, "speed": "19.49"},
{"heading": "166.9", "latitude": 6.1526394, "longitude": -75.6252285, "speed": "18.79"},
{"heading": "175.6", "latitude": 6.1524597, "longitude": -75.6252179, "speed": "18.64"},
{"heading": "180.4", "latitude": 6.1523806, "longitude": -75.6252191, "speed": "18.56"},
{"heading": "181.9", "latitude": 6.1522189, "longitude": -75.6252291, "speed": "18.59"},
{"heading": "185.6", "latitude": 6.1520081, "longitude": -75.62524, "speed": "18.46"},
{"heading": "189.1", "latitude": 6.1518318, "longitude": -75.625269, "speed": "18.49"},
{"heading": "185.8", "latitude": 6.1517204, "longitude": -75.6252902, "speed": "18.65"},
{"heading": "227.3", "latitude": 6.1515337, "longitude": -75.6253415, "speed": "17.45"},
{"heading": "254.1", "latitude": 6.1514937, "longitude": -75.6254515, "speed": "15.52"},
{"heading": "268.5", "latitude": 6.1514963, "longitude": -75.625539, "speed": "14.89"},
{"heading": "273.3", "latitude": 6.15151, "longitude": -75.625665, "speed": "14.91"},
{"heading": "274.7", "latitude": 6.1515243, "longitude": -75.6257985, "speed": "14.93"},
{"heading": "274.6", "latitude": 6.1515394, "longitude": -75.6259376, "speed": "14.95"},
{"heading": "274.2", "latitude": 6.15155, "longitude": -75.6260733, "speed": "14.94"},
{"heading": "274.2", "latitude": 6.1515615, "longitude": -75.6262084, "speed": "14.94"},
{"heading": "314.8", "latitude": 6.1515822, "longitude": -75.6263996, "speed": "12.26"},
{"heading": "325.1", "latitude": 6.1516644, "longitude": -75.6264633, "speed": "11.50"},
{"heading": "330.4", "latitude": 6.1517586, "longitude": -75.6265186, "speed": "11.37"},
{"heading": "331.7", "latitude": 6.1518483, "longitude": -75.626567, "speed": "11.28"},
{"heading": "34.2", "latitude": 6.1519308, "longitude": -75.6266058, "speed": "9.76"},
{"heading": "44.3", "latitude": 6.1519976, "longitude": -75.6265388, "speed": "10.71"},
{"heading": "40.1", "latitude": 6.1520697, "longitude": -75.6264616, "speed": "10.95"},
{"heading": "39.2", "latitude": 6.1521451, "longitude": -75.6263968, "speed": "10.94"},
{"heading": "39.1", "latitude": 6.1522202, "longitude": -75.6263334, "speed": "10.93"},
{"heading": "39.0", "latitude": 6.1522967, "longitude": -75.6262701, "speed": "10.93"},
{"heading": "40.8", "latitude": 6.1523819, "longitude": -75.6261951, "speed": "10.99"},
{"heading": "41.0", "latitude": 6.1524568, "longitude": -75.6261285, "speed": "10.94"},
{"heading": "47.9", "latitude": 6.1525531, "longitude": -75.6260238, "speed": "12.40"}]